{
"type": "FeatureCollection",
"crs": { "type": "name", "properties": { "name": "urn:ogc:def:crs:OGC:1.3:CRS84" } },
"features": [
{ "type": "Feature", "properties": { "Name": "Point 5", "descriptio": "vacant lot", "visibility": -1 }, "geometry": { "type": "Point", "coordinates": [ -83.059176318347497, 42.345982978172302 ] } }
]
}
